emergene/__init__.py
emergene/emergene.py
emergene/preprocessing/__init__.py
emergene/preprocessing/_dataFrame.py
emergene/preprocessing/_normalization.py
emergene/tools/__init__.py
emergene/tools/_emergene.py
emergene/tools/_markerGene.py
emergene/tools/_module.py
emergene/tools/_score.py
emergene/tools/_utils.py
emergene-1.0.0.dist-info/METADATA
emergene-1.0.0.dist-info/WHEEL
emergene-1.0.0.dist-info/licenses/LICENSE
emergene-1.0.0.dist-info/RECORD
