Metadata-Version: 2.4
Name: emergene
Version: 1.0.0
Summary: EMERGENE for individual cell-based differential transcriptomic analysis across conditions.
Project-URL: Documentation, https://genecell.github.io/Emergene/
Project-URL: Source, https://github.com/genecell/Emergene/
Project-URL: Homepage, https://genecell.github.io/Emergene/
Author-email: Min Dai <dai@broadinstitute.org>
Maintainer-email: Min Dai <dai@broadinstitute.org>, Vallari Shende <vshende@broadinstitute.org>
License-Expression: BSD-3-Clause
License-File: LICENSE
Classifier: Development Status :: 5 - Production/Stable
Classifier: Environment :: Console
Classifier: Framework :: Jupyter
Classifier: Intended Audience :: Developers
Classifier: Intended Audience :: Science/Research
Classifier: License :: OSI Approved :: BSD License
Classifier: Natural Language :: English
Classifier: Operating System :: MacOS :: MacOS X
Classifier: Operating System :: Microsoft :: Windows
Classifier: Operating System :: POSIX :: Linux
Classifier: Programming Language :: Python :: 3
Classifier: Programming Language :: Python :: 3.9
Classifier: Programming Language :: Python :: 3.10
Classifier: Programming Language :: Python :: 3.11
Classifier: Programming Language :: Python :: 3.12
Classifier: Topic :: Scientific/Engineering :: Bio-Informatics
Classifier: Topic :: Scientific/Engineering :: Visualization
Requires-Python: >=3.9
Requires-Dist: anndata>=0.8.0
Requires-Dist: bbknn>=1.5.0
Requires-Dist: numpy>=1.21.6
Requires-Dist: pandas>=1.4.4
Requires-Dist: scanpy>=1.9.1
Requires-Dist: scdrs>=1.0.0
Requires-Dist: scikit-learn>=1.1
Requires-Dist: scipy>=1.7.3
Requires-Dist: statsmodels>=0.13.2
Provides-Extra: dev
Requires-Dist: pre-commit; extra == 'dev'
